{
  "_class": "group",
  "booleanOperation": 0,
  "do_objectID": "745BE31F-C6DC-48E7-8DE3-4B9D6120BB3F",
  "exportOptions": {
    "_class": "exportOptions",
    "do_objectID": "A7008970-B498-43F1-99CE-37B48BACD725",
    "exportFormats": [
    ],
    "includedLayerIds": [
    ],
    "layerOptions": 0,
    "shouldTrim": false
  },
  "frame": {
    "_class": "rect",
    "constrainProportions": false,
    "do_objectID": "3389D9FD-04F3-4EE5-B1CE-2D6B85C0C012",
    "height": 28,
    "width": 524,
    "x": 24,
    "y": 310
  },
  "hasClickThrough": false,
  "isFixedToViewport": false,
  "isFlippedHorizontal": false,
  "isFlippedVertical": false,
  "isLocked": false,
  "isVisible": true,
  "layerListExpandedType": 2,
  "layers": [
    {
      "class": "group",
      "id": "4B0ACEDE-3149-4F44-B72A-626B4DCEF773"
    },
    {
      "class": "text",
      "id": "6278D415-8D72-4259-B4B7-12D14704BA06"
    }
  ],
  "name": "Group 2 Copy 2",
  "nameIsFixed": false,
  "resizingConstraint": 63,
  "resizingType": 0,
  "rotation": 0,
  "shouldBreakMaskChain": false,
  "style": {
    "_class": "style",
    "do_objectID": "CA0749B5-1611-4212-A7AE-C7CD7C892066",
    "endMarkerType": 0,
    "miterLimit": 10,
    "startMarkerType": 0,
    "windingRule": 1
  }
}