{
  "_class": "symbolInstance",
  "booleanOperation": 0,
  "do_objectID": "F6573D0E-FC30-48B1-93D8-5085E347ECEC",
  "exportOptions": {
    "_class": "exportOptions",
    "do_objectID": "A72E6ACA-5345-4E6E-8C82-901624CC3D19",
    "exportFormats": [
    ],
    "includedLayerIds": [
    ],
    "layerOptions": 0,
    "shouldTrim": false
  },
  "frame": {
    "_class": "rect",
    "constrainProportions": false,
    "do_objectID": "4DE5908D-DE50-474F-AC7D-8F64CB908555",
    "height": 60,
    "width": 260,
    "x": 0,
    "y": 0
  },
  "horizontalSpacing": 0,
  "isFixedToViewport": false,
  "isFlippedHorizontal": false,
  "isFlippedVertical": false,
  "isLocked": false,
  "isVisible": true,
  "layerListExpandedType": 0,
  "name": "Modals / Popup / Assets / Bg / Light",
  "nameIsFixed": false,
  "overrideValues": [
  ],
  "resizingConstraint": 63,
  "resizingType": 0,
  "rotation": 0,
  "scale": 1,
  "shouldBreakMaskChain": false,
  "style": {
    "_class": "style",
    "do_objectID": "5607152C-60F1-43B3-B5D7-627DA87FC608",
    "endMarkerType": 0,
    "miterLimit": 10,
    "startMarkerType": 0,
    "windingRule": 1
  },
  "symbolID": "F5B35C15-3C41-4C3C-8D5E-A549E1F9A26B",
  "verticalSpacing": 0
}