{
  "_class": "symbolInstance",
  "do_objectID": "361C08AA-8951-4C0F-A718-57418529D011",
  "exportOptions": {
    "_class": "exportOptions",
    "do_objectID": "27186EDE-BDCA-44CD-9129-D6BA9A4B6E8C",
    "exportFormats": [
    ],
    "includedLayerIds": [
    ],
    "layerOptions": 0,
    "shouldTrim": false
  },
  "frame": {
    "_class": "rect",
    "constrainProportions": true,
    "do_objectID": "3A3FFCB4-F612-41DB-8DA9-CA81E84CCBAC",
    "height": 24,
    "width": 24,
    "x": 16,
    "y": 198
  },
  "horizontalSpacing": 0,
  "isFlippedHorizontal": false,
  "isFlippedVertical": false,
  "isLocked": false,
  "isVisible": true,
  "layerListExpandedType": 0,
  "name": "Icon / Circle",
  "nameIsFixed": false,
  "overrideValues": [
  ],
  "overrides": {
  },
  "resizingConstraint": 63,
  "resizingType": 0,
  "rotation": 0,
  "scale": 1,
  "shouldBreakMaskChain": false,
  "style": {
    "_class": "style",
    "do_objectID": "333123FD-C313-46B7-BF52-192C9210B8C9",
    "endDecorationType": 0,
    "miterLimit": 10,
    "startDecorationType": 0
  },
  "symbolID": "03FC20B5-C2B2-4712-BE9E-6C816FA643CD",
  "userInfo": {
    "com.animaapp.stc-sketch-plugin": {
      "kModelPropertiesKey": {
      }
    }
  },
  "verticalSpacing": 0
}