{
  "_class": "group",
  "do_objectID": "EE810859-AADA-43C5-B996-C2C6C72BC947",
  "exportOptions": {
    "_class": "exportOptions",
    "exportFormats": [
    ],
    "includedLayerIds": [
    ],
    "layerOptions": 0,
    "shouldTrim": false
  },
  "frame": {
    "_class": "rect",
    "constrainProportions": false,
    "height": 179,
    "width": 340,
    "x": 0,
    "y": 301
  },
  "hasClickThrough": false,
  "isFlippedHorizontal": false,
  "isFlippedVertical": false,
  "isLocked": false,
  "isVisible": true,
  "layerListExpandedType": 2,
  "layers": [
    {
      "class": "shapeGroup",
      "id": "B116D579-A478-4B28-9465-044BA41546F0"
    },
    {
      "class": "group",
      "id": "DA3F437E-2EA6-49B5-9513-658ED8B08FF6"
    },
    {
      "class": "group",
      "id": "35B46D65-B18C-4029-81A9-1944BAD26F8D"
    },
    {
      "class": "group",
      "id": "FBDC4711-2875-4552-A9D4-E984D658D1D3"
    },
    {
      "class": "group",
      "id": "1DE9EC33-9542-45ED-96A7-882E0CB64193"
    },
    {
      "class": "shapeGroup",
      "id": "B62D8336-441F-483E-A878-75047ACD6841"
    },
    {
      "class": "shapeGroup",
      "id": "038B5F76-E408-4242-99C8-51C4C7CBD183"
    },
    {
      "class": "shapeGroup",
      "id": "C5A9BCC4-655C-4EA1-99C6-0A3B0F248B5E"
    },
    {
      "class": "text",
      "id": "35A2C642-4D34-4EE8-8EAE-C6C18F17B875"
    },
    {
      "class": "shapeGroup",
      "id": "63895A76-844E-405A-82FC-62CC527739FD"
    }
  ],
  "name": "Group 3",
  "nameIsFixed": false,
  "resizingConstraint": 63,
  "resizingType": 0,
  "rotation": 0,
  "shouldBreakMaskChain": false,
  "style": {
    "_class": "style",
    "endDecorationType": 0,
    "miterLimit": 10,
    "startDecorationType": 0
  },
  "userInfo": {
    "com.animaapp.stc-sketch-plugin": {
      "kModelPropertiesKey": {
      }
    }
  }
}