{
  "_class": "symbolMaster",
  "backgroundColor": {
    "_class": "color",
    "alpha": 1,
    "blue": 0,
    "green": 0,
    "red": 0
  },
  "changeIdentifier": 10,
  "do_objectID": "F593910B-D686-4923-A1A5-E3A190BCDCFD",
  "exportOptions": {
    "_class": "exportOptions",
    "exportFormats": [
    ],
    "includedLayerIds": [
    ],
    "layerOptions": 0,
    "shouldTrim": false
  },
  "frame": {
    "_class": "rect",
    "constrainProportions": false,
    "height": 480,
    "width": 340,
    "x": 415,
    "y": 1026
  },
  "grid": {
    "_class": "simpleGrid",
    "gridSize": 10,
    "isEnabled": false,
    "thickGridTimes": 2
  },
  "hasBackgroundColor": true,
  "hasClickThrough": true,
  "horizontalRulerData": {
    "_class": "rulerData",
    "base": 0,
    "guides": [
    ]
  },
  "includeBackgroundColorInExport": true,
  "includeBackgroundColorInInstance": true,
  "includeInCloudUpload": true,
  "isFlippedHorizontal": false,
  "isFlippedVertical": false,
  "isLocked": false,
  "isVisible": true,
  "layerListExpandedType": 0,
  "layers": [
    {
      "class": "text",
      "id": "2CAB9D8F-395A-4795-8075-1D1675CCB227"
    },
    {
      "class": "symbolInstance",
      "id": "8B444337-5249-4F13-826B-F78203C3AEE4"
    },
    {
      "class": "symbolInstance",
      "id": "1666D8D8-ECC5-453B-9173-42AD93A74B0A"
    },
    {
      "class": "text",
      "id": "776F97DD-34D1-422D-9BD6-2DE5AD219F8F"
    }
  ],
  "layout": {
    "_class": "layoutGrid",
    "columnWidth": 72,
    "drawHorizontal": true,
    "drawHorizontalLines": false,
    "drawVertical": true,
    "gutterHeight": 8,
    "gutterWidth": 8,
    "guttersOutside": true,
    "horizontalOffset": 0,
    "isEnabled": false,
    "numberOfColumns": 4,
    "rowHeightMultiplication": 1,
    "totalWidth": 320
  },
  "name": "System / Lockscreen / Notifications",
  "nameIsFixed": false,
  "resizesContent": false,
  "resizingConstraint": 63,
  "resizingType": 0,
  "rotation": 0,
  "shouldBreakMaskChain": true,
  "style": {
    "_class": "style",
    "endDecorationType": 0,
    "miterLimit": 10,
    "startDecorationType": 0
  },
  "symbolID": "7B73AB5B-0AF5-4EE6-AF4F-9DBA5C8C313B",
  "userInfo": {
    "io.magicsketch.mirror": {
      "highestQuality": 2
    }
  },
  "verticalRulerData": {
    "_class": "rulerData",
    "base": 0,
    "guides": [
    ]
  }
}