{
  "_class": "shapeGroup",
  "booleanOperation": 0,
  "clippingMaskMode": 0,
  "do_objectID": "6E8850D1-CFFF-413C-B550-FB4407A6F6F0",
  "exportOptions": {
    "_class": "exportOptions",
    "do_objectID": "55718D26-A2B0-4981-866E-D25BBBBF8651",
    "exportFormats": [
    ],
    "includedLayerIds": [
    ],
    "layerOptions": 0,
    "shouldTrim": false
  },
  "frame": {
    "_class": "rect",
    "constrainProportions": false,
    "do_objectID": "3998693C-A990-41C7-8EA2-04D4761DB294",
    "height": 240,
    "width": 340,
    "x": 0,
    "y": 0
  },
  "hasClickThrough": false,
  "hasClippingMask": false,
  "isFixedToViewport": false,
  "isFlippedHorizontal": false,
  "isFlippedVertical": false,
  "isLocked": false,
  "isVisible": true,
  "layerListExpandedType": 0,
  "layers": [
    {
      "class": "rectangle",
      "id": "610265F8-151C-4F79-BF93-DC10342CDCC2"
    }
  ],
  "name": "Rectangle Copy",
  "nameIsFixed": false,
  "resizingConstraint": 63,
  "resizingType": 0,
  "rotation": 0,
  "shouldBreakMaskChain": false,
  "style": {
    "sharedObjectID": "2D1E5E7C-0ACE-46AB-AF6C-458C1096B0A8"
  },
  "windingRule": 1
}